{"artist":"Nate Bowden","attack":3,"cardClass":"NEUTRAL","collectible":true,"cost":5,"dbfId":1793,"flavor":"DO NOT GIVE HIM A ROOT BEER.","health":5,"howToEarn":"Unlocked in The Plague Quarter, in the Naxxramas adventure.","howToEarnGolden":"Crafting unlocked in The Plague Quarter, in the Naxxramas adventure.","id":"FP1_012","mechanics":["DEATHRATTLE","TAUNT"],"name":"Sludge Belcher","rarity":"RARE","set":"NAXX","text":"<b>Taunt\nDeathrattle:</b> Summon a 1/2 Slime with <b>Taunt</b>.","type":"MINION"}